MANIFEST.in
README.md
requirements.txt
setup.cfg
setup.py
pdfgrep/__init__.py
pdfgrep/pdfgrep.py
pdfgrep.egg-info/PKG-INFO
pdfgrep.egg-info/SOURCES.txt
pdfgrep.egg-info/dependency_links.txt
pdfgrep.egg-info/entry_points.txt
pdfgrep.egg-info/requires.txt
pdfgrep.egg-info/top_level.txt