Metadata-Version: 1.1
Name: pdfgrep
Version: 0.10
Summary: a grep tool for pdf files
Home-page: https://github.com/adiabuk/pdfgrep
Author: Amro Diab
Author-email: adiab@linuxmail.org
License: UNKNOWN
Download-URL: https://github.com/adiabuk/pdfgrep/archive/0.10.tar.gz
Keywords: pdf,grep
Platform: UNKNOWN
